{
  "attach_pages": "4",
  "attach_size": "855",
  "attach_type": "0",
  "attach_url": "https://pdf.dfcfw.com/pdf/H3_AP202010141421290602_1.pdf?1602683574000.pdf",
  "company_code": "80045894",
  "eitime": "2020-10-14 13:52:54",
  "extend": {},
  "info_code": "AP202010141421290602",
  "language": "0",
  "notice_date": "2020-10-14 00:00:00",
  "notice_title": "分众传媒2020年三季报预告点评：三季度业绩预增97%-140%，看好公司品牌服务带来的强劲恢复增长",
  "page_size": 1,
  "page_size_ch": 0,
  "page_size_cht": 0,
  "page_size_en": 0,
  "rating": "CCC",
  "researcher": "马笑,宋尚杰",
  "security": [
    {
      "market_uni": "0",
      "publish_relation": [
        {
          "originalCode": "486",
          "publishName": "文化传媒"
        }
      ],
      "short_name": "分众传媒",
      "short_name_ch": "分众传媒",
      "short_name_cht": "分眾傳媒",
      "short_name_en": "FOCUS MEDIA",
      "stock": "002027"
    }
  ],
  "short_name": "分众传媒",
  "source_sample_name": "诚通证券",
  "star": "4"
}