{
  "attach_pages": "7",
  "attach_size": "638",
  "attach_type": "0",
  "attach_url": "https://pdf.dfcfw.com/pdf/H3_AP202309011597327715_1.pdf?1693584396000.pdf",
  "company_code": "80092742",
  "eitime": "2023-09-01 16:06:36",
  "extend": {},
  "info_code": "AP202309011597327715",
  "language": "0",
  "notice_content": "　　邮储银行(601658)\n　　事件：8月30日晚，邮储银行披露2023年中报：2023H实现营业收入1769.76亿元，同比增长2.03%；归母净利润495.64亿元，同比增长5.20%；资产规模突破15万亿元。\n　　点评：\n　　资产规模迈向15万亿新台阶，公贷及个人小额贷款支撑扩表。2023年6月末，邮储银行资产总额为15.12万亿元，同比增长15.6%。其中，公司贷款总额3.07万亿元，同比高增22%，主要是在高端制造业、新兴产业、小微金融等发力；零售层面，邮储银行对农户普遍授信、重点聚焦农村信贷等金融，个人小额贷款1.32万亿元，同比增长22.6%，支撑零售贷款增长。邮储银行常年聚焦“三农”服务体系，涉农贷款余额突破2万亿元，较上年末增加2329.64亿元，增量创历年同期新高；普惠小微贷款余额1.35万亿元，同比增长23.7%。\n　　Q2净利润环比上行，剔除理财净值化转型一次性因素影响后手续费收入亮眼。Q2单季度净利润同比增速为5.46%，环比Q1增速上行0.43pct；Q2营业收入888.13亿元，增速较Q1有所下滑。上半年手续费净收入182.03亿元，同比增长1.8%，主要是理财业务拖累，剔除掉理财业务净值化转型带来的一次性因素影响，手续费净收入同比增长24.17%，增速仍然强劲。此外，代理业务上半年增长177.9亿元，同比高增51.6%，主要是代理保险等业务收入实现快速增长。\n　　息差环比Q1下降1BP，计息负债成本率再下行。上半年邮储银行净息差为2.08%，较去年同期下行19BP，主要是经济环境承压背景下，资产端收益率下行，上半年贷款收益率4.24%，较去年同期下行37BP。公贷和个贷收益率延续下滑趋势，其中，上半年公贷收益率较去年同期下行28BP至3.65%，个贷收益率较去年同期下行39BP至4.95%。得益于邮储银行优化负债结构、注重核心存款，上半年负债成本率为1.57%，较去年同期下行8BP，一定程度上缓解了贷款利率下行带来的影响。\n　　不良率环比再降1BP，资产质量持续夯实。6月末，邮储银行不良率为0.81%，环比Q1和去年末分别下行1BP和3BP，不良贷款生成率0.78%，较上年末下降0.07pct，拨备覆盖率超380%，体现其风险抵补能力。3月移动集团450亿元溢价定增邮储银行，全部用于补充核心一级资本，支撑扩表增速提升，截至6月末，邮储银行核心一级资本充足率为9.42%，较上年末提高0.06pct。\n　　盈利预测：邮储银行具备零售基因、深耕零售多年，Q2净利润增速边际改善，揽储能力优异。不良率环比再下行，资本进一步夯实，风险抵补能力优异，我们预计公司2023-2025年归母净利润增速分别为15.40%、17.90%、15.86%。\n　　风险因素：经济超预期下行，政策出台不及预期等。\n",
  "notice_date": "2023-09-01 00:00:00",
  "notice_title": "净利润增速环比改善，资产质量持续夯实",
  "page_size": 1,
  "page_size_ch": 0,
  "page_size_cht": 0,
  "page_size_en": 0,
  "rating": "BBB",
  "researcher": "张晓辉,廖紫苑,王舫朝",
  "security": [
    {
      "market_uni": "1",
      "publish_relation": [
        {
          "originalCode": "475",
          "publishName": "银行"
        }
      ],
      "short_name": "邮储银行",
      "short_name_ch": "邮储银行",
      "short_name_cht": "郵儲銀行",
      "short_name_en": "PSBC",
      "stock": "601658"
    }
  ],
  "short_name": "邮储银行",
  "source_sample_name": "信达证券",
  "star": "3"
}