{
  "attach_pages": "4",
  "attach_size": "575",
  "attach_type": "0",
  "attach_url": "https://pdf.dfcfw.com/pdf/H3_AP201708280833958968_1.pdf?1503929153000.pdf",
  "company_code": "80050806",
  "eitime": "2017-08-28 14:06:46",
  "extend": {},
  "info_code": "AP201708280833958968",
  "language": "0",
  "notice_date": "2017-08-28 00:00:00",
  "notice_title": "南京银行半年报点评：资产质量向好，息差环比企稳",
  "page_size": 1,
  "page_size_ch": 0,
  "page_size_cht": 0,
  "page_size_en": 0,
  "rating": "CCC",
  "researcher": "孙立金",
  "security": [
    {
      "market_uni": "1",
      "publish_relation": [
        {
          "originalCode": "475",
          "publishName": "银行"
        }
      ],
      "short_name": "南京银行",
      "short_name_ch": "南京银行",
      "short_name_cht": "南京銀行",
      "short_name_en": "NJBK",
      "stock": "601009"
    }
  ],
  "short_name": "南京银行",
  "source_sample_name": "太平洋",
  "star": "3"
}