{
  "attach_pages": "23",
  "attach_size": "2547",
  "attach_type": "0",
  "attach_url": "https://pdf.dfcfw.com/pdf/H3_AP202208251577639275_1.pdf?1661453645000.pdf",
  "company_code": "10001968",
  "eitime": "2022-08-25 18:54:05",
  "extend": {},
  "info_code": "AP202208251577639275",
  "language": "0",
  "notice_content": "　　洛阳钼业(603993)\n　　2022H1业绩再创上市以来新高。洛阳钼业2022H1实现营业收入917.7亿元，同比增长8.2%，归母净利润41.5亿元，同比增长72%，归母净利润再创历史新高。2022Q2公司实现归母净利润23.6亿元，同比增长68%，环比增长31%。净利润接近此前业绩预告上限。\n　　2022H1公司矿产铜13.7万吨（+24%），钴1.05万吨（+49%），铌0.46万吨（+17%），磷肥56.5万吨（+8%），钼0.8万吨（-3%），钨0.4万吨（-2%）。\n　　截至2022H1公司持有货币资金高达296.5亿元，流动性储备充足。\n　　除了矿山板块，公司旗下埃珂森IXM金属贸易平台实现除钼、钨、磷以外的全部产品的包销，上半年完成金属贸易量（实物量）305.4万吨，实现归属于母公司净利润约0.98亿美元，同比增幅超50%。\n　　重点项目建设提速，围绕2022年度建设年目标任务稳步推进。TFM混合矿项目：中区已完成粗碎、磨机基础施工，并开始磨机主体设备安装；东区磨机基础施工完成、浸出槽基础待防腐施工。TFM铜钴矿于2023年投产后将增加铜年均产量20万吨、钴年均产量1.7万吨。\n　　KFM项目：筹建前期各项工作顺利推进，项目各项工作按照里程碑节点顺利推进，河流改道工程基本完成，选矿厂、变电站、冶炼厂、尾矿库等工程顺利开展。KFM项目在2023H1达产后，将增加铜年均产量9万吨、钴年均产量3万吨。公司铜钴产能实现大幅度提升后，洛阳钼业将成为全球最大的钴生产商。\n　　盈利预测与估值。洛阳钼业是全球铜钴龙头企业，我们预计公司2022-2024年EPS分别为0.34、0.43和0.63（分别调降3%、1%和2%）。我们认为未来2年公司TFM混合矿项目和KFM铜钴矿等将投产运营，公司净利润将迎来快速增长期，参考可比公司估值水平，给予公司2022年22倍PE估值（原为2022年26x），目标价为7.48元/股（调降18%），维持“优于大市”评级。\n　　风险提示。项目建设进度不及预期，成本控制不及预期。\n",
  "notice_date": "2022-08-25 00:00:00",
  "notice_title": "两大重磅项目提速推进，23年铜钴产能大幅跃升",
  "page_size": 1,
  "page_size_ch": 0,
  "page_size_cht": 0,
  "page_size_en": 0,
  "researcher": "施毅",
  "security": [
    {
      "market_uni": "1",
      "publish_relation": [
        {
          "originalCode": "1027",
          "publishName": "小金属"
        }
      ],
      "short_name": "洛阳钼业",
      "short_name_ch": "洛阳钼业",
      "short_name_cht": "洛陽鉬業",
      "short_name_en": "CMOC",
      "stock": "603993"
    }
  ],
  "short_name": "洛阳钼业",
  "source_sample_name": "海通国际"
}