{
  "attach_pages": "4",
  "attach_size": "642",
  "attach_type": "0",
  "attach_url": "https://pdf.dfcfw.com/pdf/H3_AP202504171657872600_1.pdf?1744901997000.pdf",
  "company_code": "80000200",
  "eitime": "2025-04-17 14:59:57",
  "extend": {},
  "info_code": "AP202504171657872600",
  "language": "0",
  "notice_content": "　　韦尔股份(603501)\n　　韦尔股份发布2024年年报。2024年公司营收257.31亿元，YoY+22%；毛利率29.4%，YoY+7.7pcts。手机和汽车CIS是收入增长的主要贡献因素，DDIC营收和毛利率短期承压车规级模拟稳步推进。维持“买入”评级。\n　　支撑评级的要点\n　　营收稳健增长，利润弹性释放。韦尔股份2024年营业收入257.31亿元，YoY+22%；毛利率29.4%，YoY+7.7pcts；归母净利润33.23亿元，YoY+498%。韦尔股份2024Q4营业收入68.22亿元，QoQ+0%，YoY+15%；毛利率29.0%，QoQ-1.5pcts，YoY+6.0pcts归母净利润9.48亿元，QoQ-6%，YoY+406%。2024年公司将部分相对成熟的产品转移至本土晶圆厂，为公司日益增长的产能需求提供保障的同时，也有助于提升生产效能。\n　　手机和汽车CIS营收双增，OV50X接力OV50H实现高端手机CIS产品升级。2024年韦尔股份CIS业务营收191.90亿元，YoY+24%，毛利率34.5%，YoY+10.5pcts。其中，手机营收98.02亿元，YoY+26%；汽车营收59.05亿元，YoY+30%。2024年公司凭借OV50H、OV50K40等高端型号在智能手机市场份额持续提升。2025年4月公司推出OV50X，像素达到5000万，像素尺寸达到1.6μm，具备拍摄高动态范围视频、优异的弱光性能、快速自动对焦和高帧率的功能。OV50X预计于2025Q3量产，将进一步丰富公司的高端手机CIS产品线。2024年公司推出OX12A10汽车CIS，具有高分辨率、出色的低光性能、LED闪烁抑制功能、小尺寸、高能效等优点。公司以3/5/8/12M的产品矩阵覆盖了ADAS、驾驶室监控、电子后视镜、仪表盘摄像头、后视、全景影像等广泛的汽车应用。\n　　DDIC营收和毛利率短期承压，车规级模拟稳步推进。2024年韦尔股份DDIC业务营收10.28亿元，YoY-18%，毛利率8.1%，YoY-1.4pcts。2024年公司DDIC销量1.55亿颗，YoY+17%；受行业供需不平衡影响，LCD-TDDI均价持续承压。公司已经开发出智能手机OLED DDIC、中尺寸屏幕TED芯片等，同时公司持续研发车规级TDDI，未来DDIC业务或触底反弹。2024年韦尔股份模拟业务营收14.22亿元，YoY+23%，毛利率35.2%，YoY-2.0pcts。2024年公司持续巩固和下游客户合作，实现市场份额稳步推进。公司将持续推进车用模拟芯片的布局，推进CAN/LIN、SerDes、PMIC、SBC等多产品的验证导入。\n　　估值\n　　考虑到2024年韦尔股份DDIC和模拟业务毛利率依然呈现下滑趋势，我们小幅下调公司2025/2026年EPS至3.62/4.19元，并预计2027年EPS为4.67元。截至2025年4月16日收盘，韦尔股份总市值约1512亿元，对应2025/2026/2027年PE分别为34.3/29.7/26.6倍。维持“买入”评级。\n　　评级面临的主要风险\n　　行业需求不及预期。市场竞争格局恶化。应用创新不及预期。供应链风险。\n",
  "notice_date": "2025-04-17 00:00:00",
  "notice_title": "手机高端化+汽车驱动增长，车规级模拟稳步推进",
  "page_size": 1,
  "page_size_ch": 0,
  "page_size_cht": 0,
  "page_size_en": 0,
  "rating": "A",
  "researcher": "苏凌瑶,茅珈恺",
  "security": [
    {
      "market_uni": "1",
      "publish_relation": [
        {
          "originalCode": "1036",
          "publishName": "半导体"
        }
      ],
      "short_name": "豪威集团",
      "short_name_ch": "豪威集团",
      "short_name_cht": "豪威集團",
      "short_name_en": "OMNIVISION GROUP",
      "stock": "603501"
    }
  ],
  "short_name": "豪威集团",
  "source_sample_name": "中银证券",
  "star": "4"
}