{
  "attach_pages": "3",
  "attach_size": "642",
  "attach_type": "0",
  "attach_url": "https://pdf.dfcfw.com/pdf/H3_AP202108291513146552_1.pdf?1630252750000.pdf",
  "company_code": "80000031",
  "eitime": "2021-08-29 15:59:10",
  "extend": {},
  "info_code": "AP202108291513146552",
  "language": "0",
  "notice_content": "　　青岛啤酒(600600)\n　　事件： 青岛啤酒发布了 2021 半年度报告， 2021H1 公司实现产品销量 476.9万千升，同增 8.2%；实现收入 182.9 亿元，同增 16.66%；实现归母净利润24.16 亿元，同增 30.22%。单 Q2 实现产品销量 257.9 万千升，同减 7.06%；实现收入 93.6 亿元，同减 2.45%；实现归母净利润 13.94 亿元，同增 5.77%。\n　　投资要点\n　　产品结构升级提速，拉动业绩持续增长。 2021H1 公司销量实现高增长，其中主品牌实现产品销量 252.8 万千升，同增 20.9%，快于整体销量增长，占总销量 53%。高档以上产品销量实现同增 41.4%。中高端的快速增长，主要系上半年公司在持续巩固传统核心基地市场的同时，加速中低端产品向中高端转化。吨酒价方面，上半年吨酒价同比提升 7.8%至3835.2 元/千升，单 Q2 吨酒价同比提升 7.4%至 3630.6 元/千升。\n　　高端化红利持续兑现，对冲原材料成本上涨。 公司 H1/Q2 毛利率分别为44.40%/43.70%，同比+2.64pct/+0.80pct。包材，大麦成本上半年上涨，而毛利率仍有显著提升，主因产品销量增加和高端化加速带来的结构优化所致。费用率方面， H1/Q2 销售费用率分别为 18.29%/14.51%，同比+0.01pct/-1.73pct；管理费用率为 3.89%/3.98%，同比+0.68pct/+1.17pct。上半年管理费用增加主要系公司实现限制性股票激励计划确认股份支付费用，以及同期因新冠疫情影响政府减免社会保险费用所致。\n　　H2 主次品牌同步推进，费用释放推动盈利上行。 公司继续推进“ 双品牌”战略。通过沉浸式品牌推广模式构建消费场景多元化，打造终端生态圈，截至报告期，在全国已布局 200 多家“ TSINGTAO1903 青岛啤酒吧”。 H2 公司有望通过释放费用， 保障优势市场中低端产品渗透率，通过结构升级转化，继续加速高端化进程，实现盈利水平将持续上行。\n　　盈利预测与投资评级： 我们预计公司在产品结构升级驱动下，盈利能力平稳提升。我们将 2021-2023 年公司营业收入从 308/339/367 亿元调整为 303/319/335 亿元，实现归母净利润从 27.8/34.0/40.1 亿元调整为24.8/29.2/32.8 亿元；当前股价对应 PE 为 48/41/37 倍,维持“买入”评级。\n　　风险提示： 高端化进程不如预期，原材料成本上涨，中低端市场掌控力减弱。\n",
  "notice_date": "2021-08-29 00:00:00",
  "notice_title": "2021年中报点评：业绩超市场预期，结构升级步伐持续增速",
  "page_size": 1,
  "page_size_ch": 0,
  "page_size_cht": 0,
  "page_size_en": 0,
  "rating": "A",
  "researcher": "何长天",
  "security": [
    {
      "market_uni": "1",
      "publish_relation": [
        {
          "originalCode": "477",
          "publishName": "酿酒行业"
        }
      ],
      "short_name": "青岛啤酒",
      "short_name_ch": "青岛啤酒",
      "short_name_cht": "青島啤酒",
      "short_name_en": "TSINGTAO BREWERY",
      "stock": "600600"
    }
  ],
  "short_name": "青岛啤酒",
  "source_sample_name": "东吴证券",
  "star": "3"
}