{
  "attach_pages": "4",
  "attach_size": "375",
  "attach_type": "0",
  "attach_url": "https://pdf.dfcfw.com/pdf/H3_AP202407171638005453_1.pdf?1721238723000.pdf",
  "company_code": "80000064",
  "eitime": "2024-07-17 17:52:03",
  "extend": {},
  "info_code": "AP202407171638005453",
  "language": "0",
  "notice_content": "　　温氏股份(300498)\n　　主要观点：\n　　24Q2归母净利润24.86亿元-27.36亿元，同环比扭亏为盈\n　　公司公布2024年半年度业绩预告：归母净利润12.5亿元-15亿元，扣非后归母净利润13亿元-15.5亿元，同比扭亏为盈。分季度看，Q1、Q2分别实现归母净利润-12.36亿元，24.86亿元-27.36亿元，Q2业绩同环比扭亏为盈。\n　　预计24Q2生猪业务盈利约18亿元，养殖综合成本较Q1明显回落\n　　1H2024，公司出栏生猪1437.42万头，同比增长22.0%，已完成全年出栏目标3000-3300万头43.6%-47.9%。毛猪销售均价15.32元/公斤，同比上升5.1%。分季度看，2024Q1、Q2公司生猪出栏量718万头、719万头，同比分别增长28.3%、16.2%，实现生猪业务收入123.1亿元、145亿元，同比分别增长24.4%、33.9%。分月度看，4-6月公司生猪销售均价分别为15.18元/公斤、15.83元/公斤、18.1元/公斤；公司坚持做好基础生产管理，生产保持稳定，生产成绩持续向好，同时叠加饲料原料价格下降，4-5月公司生猪养殖综合成本分别降至14.4元/公斤、14.2元/公斤，较Q1的15.2元/公斤明显下降，我们估计6月成本14.2元/公斤左右，由此推算Q2生猪业务盈利约18亿元。随着生产效率的逐步提升，公司生猪综合成本仍有下行空间。\n　　预计2024Q2肉鸡业务盈利约9亿元，肉鸡完全成本稳步回落\n　　1H2024公司肉鸡出栏量5.48亿羽，同比减少1.0%，毛鸡销售均价13.29元/公斤，同比上升1.5%。分季度看，2024Q1、Q2公司肉鸡出栏量2.67亿羽、2.8亿羽，同比分别增长0.2%、-1.1%，实现肉鸡业务收入76.52亿元、80.21亿元，同比分别增长-1.0%、-1.2%。分月度看，4-6月公司肉鸡销售均价分别为13.21元/公斤、13.83元/公斤、13.68元/公斤，4-5月公司肉鸡完全成本分别降至约12.2元/公斤、12元/公斤，我们估计6月成本在12元/公斤左右，由此推算Q2肉鸡业务盈利约9亿元。\n　　生猪价格高点值得期待，黄羽鸡有望获得正常盈利\n　　①本轮周期2022年12月-2024年4月累计去化9.2%，去化已超过\n　　2021-2022年，较2021年6月能繁母猪存栏量下降12.5%。今年3月以来，生猪价格持续超市场预期，我们判断与2023Q4生猪疫情较严重带来的供需缺口直接相关，当然，二育和压栏也对猪价有一定提振，随着产能去化的影响不断显现，本轮猪价高点值得期待；此外，受亏损期较长、高资产负债率维持数年、偏好压栏和二育等因素影响，生猪产能回升速度偏慢；②2024年第24周（6.10-6.16）：黄羽在产祖代存栏151.06万套，处于2018年以来同期高位；黄羽在产父母代存栏1334.1万套，处于2018年以来同期最低水平；黄羽父母代鸡苗销量131.3万套，高于2022年、2023年同期水平，2024年黄羽鸡产业链有望获得正常盈利。\n　　投资建议\n　　我们预计2024-2026年公司生猪出栏量3300万头、3700万头、4000万头，同比分别增长25.7%、12.1%、8.1%，预计肉鸡出栏量12.42亿羽、13.04亿羽、13.69亿羽，同比分别增长5%、5%、5%，对应归母净利润102.57亿元、154.5亿元、129.55亿元，同比分别增长260.5%、50.6%、-16.1%，归母净利润前值2024年84.03亿元、2025年175.3亿元、2026年153.62亿元，本次调整幅度较大的原因是，修正了24-26年猪价、鸡价预期、生猪养殖综合成本。2024年生猪价格有望迎来新一轮上行周期，公司作为我国第二大生猪养殖企业、第一大黄羽鸡养殖企业，有望实现净利润大幅增长，维持公司“买入”评级不变。\n　　风险提示\n　　疫情；鸡价上涨晚于预期；猪价持续低迷。\n",
  "notice_date": "2024-07-17 00:00:00",
  "notice_title": "Q2同环比扭亏为盈，畜禽成本稳步回落",
  "page_size": 1,
  "page_size_ch": 0,
  "page_size_cht": 0,
  "page_size_en": 0,
  "rating": "A",
  "researcher": "王莺",
  "security": [
    {
      "market_uni": "0",
      "publish_relation": [
        {
          "originalCode": "433",
          "publishName": "农牧饲渔"
        }
      ],
      "short_name": "温氏股份",
      "short_name_ch": "温氏股份",
      "short_name_cht": "溫氏股份",
      "short_name_en": "WENS",
      "stock": "300498"
    }
  ],
  "short_name": "温氏股份",
  "source_sample_name": "华安证券",
  "star": "4"
}