{
  "attach_pages": "4",
  "attach_size": "430",
  "attach_type": "0",
  "attach_url": "https://pdf.dfcfw.com/pdf/H3_AP202511011772849361_1.pdf?1761968130000.pdf",
  "company_code": "80000031",
  "eitime": "2025-11-01 03:35:30",
  "extend": {},
  "info_code": "AP202511011772849361",
  "language": "0",
  "notice_content": "　　东方证券(600958)\n　　投资要点\n　　事件：东方证券发布2025年三季报。25Q1~3实现营业收入127.1亿元，可比口径下同比+39.4%；归母净利润51.1亿元，同比+54.8%；对应EPS0.59元，ROE6.4%，同比+2.2pct。第三季度实现营业收入47.1亿元，可比口径下同比+40.3%；归母净利润16.5亿元，同比+38.3%，环比-18.8%。\n　　Q3经纪业务收入同比增幅显著：1）25Q1~3经纪业务收入23.8亿元，同比+49.1%，占营业收入比重17.2%；其中Q3单季度经纪业务收入10.1亿元，同比+83.2%。25Q1~3全市场日均股基交易额18723亿元，同比+108.6%。2）截至25Q3末公司两融余额356亿元，较年初+27%，市场份额1.5%，较年初基本持平，全市场两融余额23942亿元，较年初+28.4%。\n　　投行业务收入同比大幅提升，股权承销规模显著回升：25Q1~3公司投行业务收入11.7亿元，同比+41.1%，其中Q3单季度投行业务收入4.5亿元，同比+59.4%。1）股权业务：25Q1~3公司股权主承销规模142.2亿元，同比+589.2%，排名第12；其中IPO3家，募资规模17亿元；再融资11家，承销规模125亿元。公司IPO储备项目4家，排名第12，其中两市主板2家，北交所1家，创业板1家。2）债券业务：25Q1~3公司债券主承销规模4451亿元，同比+25.3%，排名第9；其中地方政府债、公司债、金融债承销规模分别为2258亿元、874亿元、783亿元。\n　　资管业务收入同比小幅下滑：25Q1~3资管业务收入9.7亿元，同比-4.3%，其中Q3单季度资管业务收入3.7亿元，同比+20.6%。截至2025H1公司资产管理规模2338亿元，同比+3.9%。\n　　前三季度自营收入同比提升：25Q1~3投资收益（含公允价值）62.0亿元，同比+54.7%；Q3单季度调整后投资净收益（含公允价值、汇兑损益、其他综合收益）7.6亿元，同比-47.3%，主要系其他债权投资公允价值变动减少导致其他综合收益下滑。\n　　盈利预测与投资评级：结合公司2025年前三季度经营情况，我们维持此前盈利预测，预计公司2025-2027年归母净利润分别为73.39/77.84/82.46亿元，对应增速分别为119.06%/6.07%/5.93%，当前市值对应2025-2027年PB估值分别为1.19x/1.13x/1.08x。看好交投活跃度回升背景下公司在财富管理转型及基金管理方面的增量，维持“买入”评级。\n　　风险提示：交易量持续走低，权益市场波动加剧致投资收益持续下滑。\n",
  "notice_date": "2025-11-01 00:00:00",
  "notice_title": "2025年三季报点评：Q3净利润同比提升近40%，费类业务收入普遍增长",
  "page_size": 1,
  "page_size_ch": 0,
  "page_size_cht": 0,
  "page_size_en": 0,
  "rating": "A",
  "researcher": "孙婷,罗宇康",
  "security": [
    {
      "market_uni": "1",
      "publish_relation": [
        {
          "originalCode": "473",
          "publishName": "证券"
        }
      ],
      "short_name": "东方证券",
      "short_name_ch": "东方证券",
      "short_name_cht": "東方證券",
      "short_name_en": "DFZQ",
      "stock": "600958"
    }
  ],
  "short_name": "东方证券",
  "source_sample_name": "东吴证券",
  "star": "3"
}