{
  "attach_pages": "7",
  "attach_size": "899",
  "attach_type": "0",
  "attach_url": "https://pdf.dfcfw.com/pdf/H3_AP202504011649841103_1.pdf?1743521165000.pdf",
  "company_code": "80000007",
  "eitime": "2025-04-01 10:50:23",
  "extend": {},
  "info_code": "AP202504011649841103",
  "language": "0",
  "notice_content": "　　中信特钢(000708)\n　　核心观点\n　　2024年公司归母净利润同比下降10%。2024年实现营收1092亿元（同比-4.2%），归母净利润51.3亿元（-10.4%），扣非归母净利润49.7亿元（-5.5%），经营性净现金流107.4亿元（+0.8%）。2024年公司钢材销量1889万吨，同比持平，其中出口220万吨，同比减少18万吨。公司年度利润分配预案：向全体股东派发现金股利25.6亿元（含税），占2024年归母净利润的49.95%。自2018年以来，公司已连续7年分红比例接近或超过50%，最近7年累计现金分红比例达到52.5%。\n　　分板块来看，重点品牌产品轴承钢销量同比增长6%，能源用钢销量创历史新高。下游行业分布，汽车行业营收占比同比增加0.2个百分点，轴承行业营收占比同比增加0.3个百分点。各子公司情况，2024年兴澄特钢净利润37.6亿元，同比下降4.8%，净利率8.7%，同比下降0.4个百分点；2024年大冶特钢净利润7.6亿元，同比下降21%，净利率2.7%，同比下降0.6个百分点；青岛特钢净利润7.8亿元，同比增长121%，净利率3.3%，同比增加1.8个百分点；天津钢管净利润6.8亿元，净利率3.2%。\n　　顶住行业周期波动，现金流强劲。近年来钢铁全行业面临下游需求恢复不振、钢材价格下跌、原料成本高企等挑战，行业整体效益处于近年来低位；行业总体过剩格局下，部分普钢企业向特钢转型，加剧特钢行业竞争，尤其是一般用途产品的同质化竞争。面对严峻局面，公司降本增效，根据下游需求变动灵活调整产品结构；另外保持较高比例研发开支，以保持产品升级迭代节奏，持续增强产品竞争力。从2024年经营情况来看公司顶住了行业周期波动，维持了强劲的现金流。同时公司积极谋划海外布局，明确了“资源+主业+分销”全产业链布局的国际化战略，遴选出重点项目进行推进并取得了积极进展。\n　　风险提示：钢材需求下滑，市场竞争加剧，原辅料价格抬升。\n　　投资建议：维持“优于大市”评级\n　　预计2025-2027年收入1106/1120/1234亿元，归母净利润57.2/61.2/66.0亿元，同比增速11.5/7.0/7.9%；摊薄EPS分别为1.13/1.21/1.31元，当前股价对应PE分别为11.0/10.3/9.5x。公司作为特钢龙头企业，成长路径清晰，市场地位突出，经营业绩稳健，属于特钢行业稀缺标的，在行业整体承压的背景下，公司稳健经营体现弱周期属性。维持“优于大市”评级。\n",
  "notice_date": "2025-04-01 00:00:00",
  "notice_title": "积极调整产品结构，盈利能力稳健",
  "page_size": 1,
  "page_size_ch": 0,
  "page_size_cht": 0,
  "page_size_en": 0,
  "rating": "AA",
  "researcher": "刘孟峦,焦方冉",
  "security": [
    {
      "market_uni": "0",
      "publish_relation": [
        {
          "originalCode": "479",
          "publishName": "钢铁行业"
        }
      ],
      "short_name": "中信特钢",
      "short_name_ch": "中信特钢",
      "short_name_cht": "中信特鋼",
      "short_name_en": "CITIC Steel",
      "stock": "000708"
    }
  ],
  "short_name": "中信特钢",
  "source_sample_name": "国信证券",
  "star": "1"
}