{
  "attach_pages": "5",
  "attach_size": "771",
  "attach_type": "0",
  "attach_url": "https://pdf.dfcfw.com/pdf/H3_AP202510311772558226_1.pdf?1761928241000.pdf",
  "company_code": "80092742",
  "eitime": "2025-10-31 16:30:41",
  "extend": {},
  "info_code": "AP202510311772558226",
  "language": "0",
  "notice_content": "　　新奥股份(600803)\n　　事件：10月30日晚，公司发布2025年第三季度业绩公告，2025年前三季度公司实现营业收入958.56亿元，同比减少2.91%；实现归母净利润34.26亿元，同比减少1.87%；实现扣非后归母净利润32.80亿元，同比增长11.39%；实现核心利润37.77亿元，同比减少1.04%；实现基本每股核心收益1.23元。\n　　2025Q3公司实现营业收入298.65亿元，同比减少5.93%；实现归母净利润10.18亿元，同比增长5.89%；实现扣非后归母净利润8.66亿元，同比减少9.01%；实现核心利润10.41亿元，同比下降6.89%。\n　　点评：\n　　2025前三季度公司各项主要业务经营情况相对稳健。1）零售气：公司零售气量稳健增长，但增速有所放缓。2025Q3公司实现零售气量62.4亿方，同比增长2.1%。2025年前三季度，公司实现零售气量191.9亿方，同比增长2.0%。其中，工商业气量152.1亿方，同比增长2.5%，民用气38亿方，同比增长1.5%。2）平台气：平台气量有所下滑，接收站周转率显著提升。2025Q3公司实现平台交易气量12.6亿方，同比下降7.1%。2025年前三季度公司实现平台交易气量39.5亿方，同比下降2.8%。其中，海外平台交易气销售气量14.3亿方，同比下滑2.7%；国内平台气销售气量25.2亿方，同比下滑3.1%。受国际天然气价格高企且国内整体供应相对充足影响，中国前三季度LNG进口量同比下跌17%，公司通过三方引流、生态合作等方式，前三季度舟山接收站接卸量达198万吨，同比增长14.2%。3）泛能业务：泛能项目稳步扩张，装机规模稳健增长。2025年前三季度，公司实现泛能销售量289.9亿千瓦时，其中冷热占比50.6%，汽占比45.1%，电占比4.3%。\n　　私有化进展顺利，交易完成后有望加强上下游一体化协同。2025年3月26日晚，新奥股份发布重大资产购买暨关联交易预案，拟对港股公司新奥能源进行私有化。截至2025年三季报，公司已向香港联交所递交了本次介绍上市的申请，并已向中国证监会报送了本次介绍上市的备案申请材料并获中国证监会接收，已完成国家发展和改革委员会备案程序。本次交易完成后，A股EPS有望增厚，上市公司与标的公司有望更好发挥协同效应。\n　　2025-2029年合计870万吨的海外长协有望放量；舟山三期接收站全面建成，处理能力提升至1000万吨/年。截止2024年底，新奥股份在执行长协约206万吨/年，公司预计2025/2026/2027/2028/2029年分别有60/180/200/160/270万吨的增量长协将开始执行，支撑直销气业务的高速扩张。此外，2025年8月6日舟山大型液化天然气（LNG）接收站三期项目正式投运，三期项目新增4座22万立方米，储罐总罐容达152万立方米，年接卸能力从500万吨提升至1000万吨。\n　　2026-2028年分红比例不低于核心利润的50%，高股息有望带动公司价值提升。公司2025年的分红计划仍执行《新奥股份未来三年（2023-2025年）股东分红回报规划》以及出售新能矿业100%股权所得投资收益的三年特别派息，即合计每股不低于1.14元（含税）。2026年至2028年公司承诺每年现金分红比例不少于当年归属于上市公司股东的核心利润的50%。\n　　盈利预测及评级：新奥股份具备天然气全产业链优势，有助于抵御气价波动，支撑盈利的持续稳健增长。私有化港股新奥能源后，公司EPS有望增厚，上下游一体化协同效益有望增强。零售气业务上游资源池成本优化，下游顺价持续推进，城燃毛差有望进一步修复，零售气量有望稳健增长，推动公司城燃业务盈利提升。直销气业务25-29年共870万吨/年的长协气源有望放量，下游市场快速开拓，有望推动直销气业务的稳健增长。暂不考虑私有化新奥能源的影响，我们预测新奥股份2025-2027年核心归母净利润分别为57.18亿元、64.10亿元、71.11亿元，EPS分别为1.85元、2.07元、2.30元，对应10月30日收盘价的PE分别为10.43/9.30/8.38倍，维持“买入”评级。\n　　风险因素：国内宏观经济增长不及预期，天然气消费量增速不及预期；接收站项目建设进度低于预期；国内天然气顺价程度不及预期；综合能源销售量低于预期；私有化进程不及预期。\n",
  "notice_date": "2025-10-31 00:00:00",
  "notice_title": "零售气业务平稳增长，平台气量有所承压",
  "page_size": 1,
  "page_size_ch": 0,
  "page_size_cht": 0,
  "page_size_en": 0,
  "rating": "BBB",
  "researcher": "李春驰,唐婵玉",
  "security": [
    {
      "market_uni": "1",
      "publish_relation": [
        {
          "originalCode": "1028",
          "publishName": "燃气"
        }
      ],
      "short_name": "新奥股份",
      "short_name_ch": "新奥股份",
      "short_name_cht": "新奧股份",
      "short_name_en": "ENNNG",
      "stock": "600803"
    }
  ],
  "short_name": "新奥股份",
  "source_sample_name": "信达证券",
  "star": "3"
}